
[{"uid":"Microsoft.Azure.Management.Storage","href":"Microsoft.Azure.Management.Storage.html","homepage":"Microsoft.Azure.Management.Storage.IStorageAccountOperations.html","homepageUid":"Microsoft.Azure.Management.Storage.IStorageAccountOperations","toc_title":"Microsoft.Azure.Management.Storage","level":1,"relative_path_in_depot":"api/storage/Microsoft.Azure.Management.Storage.html","children":[{"uid":"Microsoft.Azure.Management.Storage.IStorageAccountOperations","href":"Microsoft.Azure.Management.Storage.IStorageAccountOperations.html","toc_title":"IStorageAccountOperations","level":2,"relative_path_in_depot":"api/storage/Microsoft.Azure.Management.Storage.IStorageAccountOperations.html"},{"uid":"Microsoft.Azure.Management.Storage.IStorageManagementClient","href":"Microsoft.Azure.Management.Storage.IStorageManagementClient.html","toc_title":"IStorageManagementClient","level":2,"relative_path_in_depot":"api/storage/Microsoft.Azure.Management.Storage.IStorageManagementClient.html"},{"uid":"Microsoft.Azure.Management.Storage.IUsageOperations","href":"Microsoft.Azure.Management.Storage.IUsageOperations.html","toc_title":"IUsageOperations","level":2,"relative_path_in_depot":"api/storage/Microsoft.Azure.Management.Storage.IUsageOperations.html"},{"uid":"Microsoft.Azure.Management.Storage.StorageAccountOperationsExtensions","href":"Microsoft.Azure.Management.Storage.StorageAccountOperationsExtensions.html","toc_title":"StorageAccountOperationsExtensions","level":2,"relative_path_in_depot":"api/storage/Microsoft.Azure.Management.Storage.StorageAccountOperationsExtensions.html"},{"uid":"Microsoft.Azure.Management.Storage.StorageManagementClient","href":"Microsoft.Azure.Management.Storage.StorageManagementClient.html","toc_title":"StorageManagementClient","level":2,"relative_path_in_depot":"api/storage/Microsoft.Azure.Management.Storage.StorageManagementClient.html"},{"uid":"Microsoft.Azure.Management.Storage.StorageManagementClientExtensions","href":"Microsoft.Azure.Management.Storage.StorageManagementClientExtensions.html","toc_title":"StorageManagementClientExtensions","level":2,"relative_path_in_depot":"api/storage/Microsoft.Azure.Management.Storage.StorageManagementClientExtensions.html"},{"uid":"Microsoft.Azure.Management.Storage.UsageOperationsExtensions","href":"Microsoft.Azure.Management.Storage.UsageOperationsExtensions.html","toc_title":"UsageOperationsExtensions","level":2,"relative_path_in_depot":"api/storage/Microsoft.Azure.Management.Storage.UsageOperationsExtensions.html"}]},{"uid":"Microsoft.Azure.Management.Storage.Models","href":"Microsoft.Azure.Management.Storage.Models.html","homepage":"Microsoft.Azure.Management.Storage.Models.AccountStatus.html","homepageUid":"Microsoft.Azure.Management.Storage.Models.AccountStatus","toc_title":"Microsoft.Azure.Management.Storage.Models","level":1,"relative_path_in_depot":"api/storage/Microsoft.Azure.Management.Storage.Models.html","children":[{"uid":"Microsoft.Azure.Management.Storage.Models.AccountStatus","href":"Microsoft.Azure.Management.Storage.Models.AccountStatus.html","toc_title":"AccountStatus","level":2,"relative_path_in_depot":"api/storage/Microsoft.Azure.Management.Storage.Models.AccountStatus.html"},{"uid":"Microsoft.Azure.Management.Storage.Models.AccountType","href":"Microsoft.Azure.Management.Storage.Models.AccountType.html","toc_title":"AccountType","level":2,"relative_path_in_depot":"api/storage/Microsoft.Azure.Management.Storage.Models.AccountType.html"},{"uid":"Microsoft.Azure.Management.Storage.Models.CheckNameAvailabilityResponse","href":"Microsoft.Azure.Management.Storage.Models.CheckNameAvailabilityResponse.html","toc_title":"CheckNameAvailabilityResponse","level":2,"relative_path_in_depot":"api/storage/Microsoft.Azure.Management.Storage.Models.CheckNameAvailabilityResponse.html"},{"uid":"Microsoft.Azure.Management.Storage.Models.CustomDomain","href":"Microsoft.Azure.Management.Storage.Models.CustomDomain.html","toc_title":"CustomDomain","level":2,"relative_path_in_depot":"api/storage/Microsoft.Azure.Management.Storage.Models.CustomDomain.html"},{"uid":"Microsoft.Azure.Management.Storage.Models.Endpoints","href":"Microsoft.Azure.Management.Storage.Models.Endpoints.html","toc_title":"Endpoints","level":2,"relative_path_in_depot":"api/storage/Microsoft.Azure.Management.Storage.Models.Endpoints.html"},{"uid":"Microsoft.Azure.Management.Storage.Models.ProvisioningState","href":"Microsoft.Azure.Management.Storage.Models.ProvisioningState.html","toc_title":"ProvisioningState","level":2,"relative_path_in_depot":"api/storage/Microsoft.Azure.Management.Storage.Models.ProvisioningState.html"},{"uid":"Microsoft.Azure.Management.Storage.Models.Reason","href":"Microsoft.Azure.Management.Storage.Models.Reason.html","toc_title":"Reason","level":2,"relative_path_in_depot":"api/storage/Microsoft.Azure.Management.Storage.Models.Reason.html"},{"uid":"Microsoft.Azure.Management.Storage.Models.StorageAccount","href":"Microsoft.Azure.Management.Storage.Models.StorageAccount.html","toc_title":"StorageAccount","level":2,"relative_path_in_depot":"api/storage/Microsoft.Azure.Management.Storage.Models.StorageAccount.html"},{"uid":"Microsoft.Azure.Management.Storage.Models.StorageAccountCreateParameters","href":"Microsoft.Azure.Management.Storage.Models.StorageAccountCreateParameters.html","toc_title":"StorageAccountCreateParameters","level":2,"relative_path_in_depot":"api/storage/Microsoft.Azure.Management.Storage.Models.StorageAccountCreateParameters.html"},{"uid":"Microsoft.Azure.Management.Storage.Models.StorageAccountCreateResponse","href":"Microsoft.Azure.Management.Storage.Models.StorageAccountCreateResponse.html","toc_title":"StorageAccountCreateResponse","level":2,"relative_path_in_depot":"api/storage/Microsoft.Azure.Management.Storage.Models.StorageAccountCreateResponse.html"},{"uid":"Microsoft.Azure.Management.Storage.Models.StorageAccountGetPropertiesResponse","href":"Microsoft.Azure.Management.Storage.Models.StorageAccountGetPropertiesResponse.html","toc_title":"StorageAccountGetPropertiesResponse","level":2,"relative_path_in_depot":"api/storage/Microsoft.Azure.Management.Storage.Models.StorageAccountGetPropertiesResponse.html"},{"uid":"Microsoft.Azure.Management.Storage.Models.StorageAccountKeys","href":"Microsoft.Azure.Management.Storage.Models.StorageAccountKeys.html","toc_title":"StorageAccountKeys","level":2,"relative_path_in_depot":"api/storage/Microsoft.Azure.Management.Storage.Models.StorageAccountKeys.html"},{"uid":"Microsoft.Azure.Management.Storage.Models.StorageAccountListKeysResponse","href":"Microsoft.Azure.Management.Storage.Models.StorageAccountListKeysResponse.html","toc_title":"StorageAccountListKeysResponse","level":2,"relative_path_in_depot":"api/storage/Microsoft.Azure.Management.Storage.Models.StorageAccountListKeysResponse.html"},{"uid":"Microsoft.Azure.Management.Storage.Models.StorageAccountListResponse","href":"Microsoft.Azure.Management.Storage.Models.StorageAccountListResponse.html","toc_title":"StorageAccountListResponse","level":2,"relative_path_in_depot":"api/storage/Microsoft.Azure.Management.Storage.Models.StorageAccountListResponse.html"},{"uid":"Microsoft.Azure.Management.Storage.Models.StorageAccountRegenerateKeyResponse","href":"Microsoft.Azure.Management.Storage.Models.StorageAccountRegenerateKeyResponse.html","toc_title":"StorageAccountRegenerateKeyResponse","level":2,"relative_path_in_depot":"api/storage/Microsoft.Azure.Management.Storage.Models.StorageAccountRegenerateKeyResponse.html"},{"uid":"Microsoft.Azure.Management.Storage.Models.StorageAccountUpdateParameters","href":"Microsoft.Azure.Management.Storage.Models.StorageAccountUpdateParameters.html","toc_title":"StorageAccountUpdateParameters","level":2,"relative_path_in_depot":"api/storage/Microsoft.Azure.Management.Storage.Models.StorageAccountUpdateParameters.html"},{"uid":"Microsoft.Azure.Management.Storage.Models.StorageAccountUpdateResponse","href":"Microsoft.Azure.Management.Storage.Models.StorageAccountUpdateResponse.html","toc_title":"StorageAccountUpdateResponse","level":2,"relative_path_in_depot":"api/storage/Microsoft.Azure.Management.Storage.Models.StorageAccountUpdateResponse.html"},{"uid":"Microsoft.Azure.Management.Storage.Models.Usage","href":"Microsoft.Azure.Management.Storage.Models.Usage.html","toc_title":"Usage","level":2,"relative_path_in_depot":"api/storage/Microsoft.Azure.Management.Storage.Models.Usage.html"},{"uid":"Microsoft.Azure.Management.Storage.Models.UsageListResponse","href":"Microsoft.Azure.Management.Storage.Models.UsageListResponse.html","toc_title":"UsageListResponse","level":2,"relative_path_in_depot":"api/storage/Microsoft.Azure.Management.Storage.Models.UsageListResponse.html"},{"uid":"Microsoft.Azure.Management.Storage.Models.UsageName","href":"Microsoft.Azure.Management.Storage.Models.UsageName.html","toc_title":"UsageName","level":2,"relative_path_in_depot":"api/storage/Microsoft.Azure.Management.Storage.Models.UsageName.html"},{"uid":"Microsoft.Azure.Management.Storage.Models.UsageUnit","href":"Microsoft.Azure.Management.Storage.Models.UsageUnit.html","toc_title":"UsageUnit","level":2,"relative_path_in_depot":"api/storage/Microsoft.Azure.Management.Storage.Models.UsageUnit.html"}]}]
