
[{"uid":"Microsoft.Azure.Management.HDInsight","href":"Microsoft.Azure.Management.HDInsight.html","homepage":"Microsoft.Azure.Management.HDInsight.ClusterOperationsExtensions.html","homepageUid":"Microsoft.Azure.Management.HDInsight.ClusterOperationsExtensions","toc_title":"Microsoft.Azure.Management.HDInsight","level":1,"relative_path_in_depot":"api/hdinsight/Microsoft.Azure.Management.HDInsight.html","children":[{"uid":"Microsoft.Azure.Management.HDInsight.ClusterOperationsExtensions","href":"Microsoft.Azure.Management.HDInsight.ClusterOperationsExtensions.html","toc_title":"ClusterOperationsExtensions","level":2,"relative_path_in_depot":"api/hdinsight/Microsoft.Azure.Management.HDInsight.ClusterOperationsExtensions.html"},{"uid":"Microsoft.Azure.Management.HDInsight.ConfigurationKey","href":"Microsoft.Azure.Management.HDInsight.ConfigurationKey.html","toc_title":"ConfigurationKey","level":2,"relative_path_in_depot":"api/hdinsight/Microsoft.Azure.Management.HDInsight.ConfigurationKey.html"},{"uid":"Microsoft.Azure.Management.HDInsight.HDInsightManagementClient","href":"Microsoft.Azure.Management.HDInsight.HDInsightManagementClient.html","toc_title":"HDInsightManagementClient","level":2,"relative_path_in_depot":"api/hdinsight/Microsoft.Azure.Management.HDInsight.HDInsightManagementClient.html"},{"uid":"Microsoft.Azure.Management.HDInsight.HDInsightManagementClientExtensions","href":"Microsoft.Azure.Management.HDInsight.HDInsightManagementClientExtensions.html","toc_title":"HDInsightManagementClientExtensions","level":2,"relative_path_in_depot":"api/hdinsight/Microsoft.Azure.Management.HDInsight.HDInsightManagementClientExtensions.html"},{"uid":"Microsoft.Azure.Management.HDInsight.IClusterOperations","href":"Microsoft.Azure.Management.HDInsight.IClusterOperations.html","toc_title":"IClusterOperations","level":2,"relative_path_in_depot":"api/hdinsight/Microsoft.Azure.Management.HDInsight.IClusterOperations.html"},{"uid":"Microsoft.Azure.Management.HDInsight.IHDInsightManagementClient","href":"Microsoft.Azure.Management.HDInsight.IHDInsightManagementClient.html","toc_title":"IHDInsightManagementClient","level":2,"relative_path_in_depot":"api/hdinsight/Microsoft.Azure.Management.HDInsight.IHDInsightManagementClient.html"}]},{"uid":"Microsoft.Azure.Management.HDInsight.Models","href":"Microsoft.Azure.Management.HDInsight.Models.html","homepage":"Microsoft.Azure.Management.HDInsight.Models.AsyncOperationState.html","homepageUid":"Microsoft.Azure.Management.HDInsight.Models.AsyncOperationState","toc_title":"Microsoft.Azure.Management.HDInsight.Models","level":1,"relative_path_in_depot":"api/hdinsight/Microsoft.Azure.Management.HDInsight.Models.html","children":[{"uid":"Microsoft.Azure.Management.HDInsight.Models.AsyncOperationState","href":"Microsoft.Azure.Management.HDInsight.Models.AsyncOperationState.html","toc_title":"AsyncOperationState","level":2,"relative_path_in_depot":"api/hdinsight/Microsoft.Azure.Management.HDInsight.Models.AsyncOperationState.html"},{"uid":"Microsoft.Azure.Management.HDInsight.Models.CapabilitiesResponse","href":"Microsoft.Azure.Management.HDInsight.Models.CapabilitiesResponse.html","toc_title":"CapabilitiesResponse","level":2,"relative_path_in_depot":"api/hdinsight/Microsoft.Azure.Management.HDInsight.Models.CapabilitiesResponse.html"},{"uid":"Microsoft.Azure.Management.HDInsight.Models.Cluster","href":"Microsoft.Azure.Management.HDInsight.Models.Cluster.html","toc_title":"Cluster","level":2,"relative_path_in_depot":"api/hdinsight/Microsoft.Azure.Management.HDInsight.Models.Cluster.html"},{"uid":"Microsoft.Azure.Management.HDInsight.Models.ClusterConfigurationsResponse","href":"Microsoft.Azure.Management.HDInsight.Models.ClusterConfigurationsResponse.html","toc_title":"ClusterConfigurationsResponse","level":2,"relative_path_in_depot":"api/hdinsight/Microsoft.Azure.Management.HDInsight.Models.ClusterConfigurationsResponse.html"},{"uid":"Microsoft.Azure.Management.HDInsight.Models.ClusterCreateParameters","href":"Microsoft.Azure.Management.HDInsight.Models.ClusterCreateParameters.html","toc_title":"ClusterCreateParameters","level":2,"relative_path_in_depot":"api/hdinsight/Microsoft.Azure.Management.HDInsight.Models.ClusterCreateParameters.html"},{"uid":"Microsoft.Azure.Management.HDInsight.Models.ClusterCreateParametersExtended","href":"Microsoft.Azure.Management.HDInsight.Models.ClusterCreateParametersExtended.html","toc_title":"ClusterCreateParametersExtended","level":2,"relative_path_in_depot":"api/hdinsight/Microsoft.Azure.Management.HDInsight.Models.ClusterCreateParametersExtended.html"},{"uid":"Microsoft.Azure.Management.HDInsight.Models.ClusterCreateProperties","href":"Microsoft.Azure.Management.HDInsight.Models.ClusterCreateProperties.html","toc_title":"ClusterCreateProperties","level":2,"relative_path_in_depot":"api/hdinsight/Microsoft.Azure.Management.HDInsight.Models.ClusterCreateProperties.html"},{"uid":"Microsoft.Azure.Management.HDInsight.Models.ClusterCreateResponse","href":"Microsoft.Azure.Management.HDInsight.Models.ClusterCreateResponse.html","toc_title":"ClusterCreateResponse","level":2,"relative_path_in_depot":"api/hdinsight/Microsoft.Azure.Management.HDInsight.Models.ClusterCreateResponse.html"},{"uid":"Microsoft.Azure.Management.HDInsight.Models.ClusterDefinition","href":"Microsoft.Azure.Management.HDInsight.Models.ClusterDefinition.html","toc_title":"ClusterDefinition","level":2,"relative_path_in_depot":"api/hdinsight/Microsoft.Azure.Management.HDInsight.Models.ClusterDefinition.html"},{"uid":"Microsoft.Azure.Management.HDInsight.Models.ClusterGetProperties","href":"Microsoft.Azure.Management.HDInsight.Models.ClusterGetProperties.html","toc_title":"ClusterGetProperties","level":2,"relative_path_in_depot":"api/hdinsight/Microsoft.Azure.Management.HDInsight.Models.ClusterGetProperties.html"},{"uid":"Microsoft.Azure.Management.HDInsight.Models.ClusterGetResponse","href":"Microsoft.Azure.Management.HDInsight.Models.ClusterGetResponse.html","toc_title":"ClusterGetResponse","level":2,"relative_path_in_depot":"api/hdinsight/Microsoft.Azure.Management.HDInsight.Models.ClusterGetResponse.html"},{"uid":"Microsoft.Azure.Management.HDInsight.Models.ClusterListPersistedScriptActionsResponse","href":"Microsoft.Azure.Management.HDInsight.Models.ClusterListPersistedScriptActionsResponse.html","toc_title":"ClusterListPersistedScriptActionsResponse","level":2,"relative_path_in_depot":"api/hdinsight/Microsoft.Azure.Management.HDInsight.Models.ClusterListPersistedScriptActionsResponse.html"},{"uid":"Microsoft.Azure.Management.HDInsight.Models.ClusterListResponse","href":"Microsoft.Azure.Management.HDInsight.Models.ClusterListResponse.html","toc_title":"ClusterListResponse","level":2,"relative_path_in_depot":"api/hdinsight/Microsoft.Azure.Management.HDInsight.Models.ClusterListResponse.html"},{"uid":"Microsoft.Azure.Management.HDInsight.Models.ClusterListRuntimeScriptActionDetailResponse","href":"Microsoft.Azure.Management.HDInsight.Models.ClusterListRuntimeScriptActionDetailResponse.html","toc_title":"ClusterListRuntimeScriptActionDetailResponse","level":2,"relative_path_in_depot":"api/hdinsight/Microsoft.Azure.Management.HDInsight.Models.ClusterListRuntimeScriptActionDetailResponse.html"},{"uid":"Microsoft.Azure.Management.HDInsight.Models.ClusterNodeType","href":"Microsoft.Azure.Management.HDInsight.Models.ClusterNodeType.html","toc_title":"ClusterNodeType","level":2,"relative_path_in_depot":"api/hdinsight/Microsoft.Azure.Management.HDInsight.Models.ClusterNodeType.html"},{"uid":"Microsoft.Azure.Management.HDInsight.Models.ClusterResizeParameters","href":"Microsoft.Azure.Management.HDInsight.Models.ClusterResizeParameters.html","toc_title":"ClusterResizeParameters","level":2,"relative_path_in_depot":"api/hdinsight/Microsoft.Azure.Management.HDInsight.Models.ClusterResizeParameters.html"},{"uid":"Microsoft.Azure.Management.HDInsight.Models.ClusterRuntimeScriptActionDetailResponse","href":"Microsoft.Azure.Management.HDInsight.Models.ClusterRuntimeScriptActionDetailResponse.html","toc_title":"ClusterRuntimeScriptActionDetailResponse","level":2,"relative_path_in_depot":"api/hdinsight/Microsoft.Azure.Management.HDInsight.Models.ClusterRuntimeScriptActionDetailResponse.html"},{"uid":"Microsoft.Azure.Management.HDInsight.Models.ComputeProfile","href":"Microsoft.Azure.Management.HDInsight.Models.ComputeProfile.html","toc_title":"ComputeProfile","level":2,"relative_path_in_depot":"api/hdinsight/Microsoft.Azure.Management.HDInsight.Models.ComputeProfile.html"},{"uid":"Microsoft.Azure.Management.HDInsight.Models.ConnectivityEndpoint","href":"Microsoft.Azure.Management.HDInsight.Models.ConnectivityEndpoint.html","toc_title":"ConnectivityEndpoint","level":2,"relative_path_in_depot":"api/hdinsight/Microsoft.Azure.Management.HDInsight.Models.ConnectivityEndpoint.html"},{"uid":"Microsoft.Azure.Management.HDInsight.Models.ErrorInfo","href":"Microsoft.Azure.Management.HDInsight.Models.ErrorInfo.html","toc_title":"ErrorInfo","level":2,"relative_path_in_depot":"api/hdinsight/Microsoft.Azure.Management.HDInsight.Models.ErrorInfo.html"},{"uid":"Microsoft.Azure.Management.HDInsight.Models.ExecuteScriptActionParameters","href":"Microsoft.Azure.Management.HDInsight.Models.ExecuteScriptActionParameters.html","toc_title":"ExecuteScriptActionParameters","level":2,"relative_path_in_depot":"api/hdinsight/Microsoft.Azure.Management.HDInsight.Models.ExecuteScriptActionParameters.html"},{"uid":"Microsoft.Azure.Management.HDInsight.Models.HardwareProfile","href":"Microsoft.Azure.Management.HDInsight.Models.HardwareProfile.html","toc_title":"HardwareProfile","level":2,"relative_path_in_depot":"api/hdinsight/Microsoft.Azure.Management.HDInsight.Models.HardwareProfile.html"},{"uid":"Microsoft.Azure.Management.HDInsight.Models.HDInsightClusterProvisioningState","href":"Microsoft.Azure.Management.HDInsight.Models.HDInsightClusterProvisioningState.html","toc_title":"HDInsightClusterProvisioningState","level":2,"relative_path_in_depot":"api/hdinsight/Microsoft.Azure.Management.HDInsight.Models.HDInsightClusterProvisioningState.html"},{"uid":"Microsoft.Azure.Management.HDInsight.Models.HDInsightOperationResponse","href":"Microsoft.Azure.Management.HDInsight.Models.HDInsightOperationResponse.html","toc_title":"HDInsightOperationResponse","level":2,"relative_path_in_depot":"api/hdinsight/Microsoft.Azure.Management.HDInsight.Models.HDInsightOperationResponse.html"},{"uid":"Microsoft.Azure.Management.HDInsight.Models.HttpConnectivitySettings","href":"Microsoft.Azure.Management.HDInsight.Models.HttpConnectivitySettings.html","toc_title":"HttpConnectivitySettings","level":2,"relative_path_in_depot":"api/hdinsight/Microsoft.Azure.Management.HDInsight.Models.HttpConnectivitySettings.html"},{"uid":"Microsoft.Azure.Management.HDInsight.Models.HttpSettingsParameters","href":"Microsoft.Azure.Management.HDInsight.Models.HttpSettingsParameters.html","toc_title":"HttpSettingsParameters","level":2,"relative_path_in_depot":"api/hdinsight/Microsoft.Azure.Management.HDInsight.Models.HttpSettingsParameters.html"},{"uid":"Microsoft.Azure.Management.HDInsight.Models.LinuxOperatingSystemProfile","href":"Microsoft.Azure.Management.HDInsight.Models.LinuxOperatingSystemProfile.html","toc_title":"LinuxOperatingSystemProfile","level":2,"relative_path_in_depot":"api/hdinsight/Microsoft.Azure.Management.HDInsight.Models.LinuxOperatingSystemProfile.html"},{"uid":"Microsoft.Azure.Management.HDInsight.Models.Metastore","href":"Microsoft.Azure.Management.HDInsight.Models.Metastore.html","toc_title":"Metastore","level":2,"relative_path_in_depot":"api/hdinsight/Microsoft.Azure.Management.HDInsight.Models.Metastore.html"},{"uid":"Microsoft.Azure.Management.HDInsight.Models.OperationResource","href":"Microsoft.Azure.Management.HDInsight.Models.OperationResource.html","toc_title":"OperationResource","level":2,"relative_path_in_depot":"api/hdinsight/Microsoft.Azure.Management.HDInsight.Models.OperationResource.html"},{"uid":"Microsoft.Azure.Management.HDInsight.Models.OsProfile","href":"Microsoft.Azure.Management.HDInsight.Models.OsProfile.html","toc_title":"OsProfile","level":2,"relative_path_in_depot":"api/hdinsight/Microsoft.Azure.Management.HDInsight.Models.OsProfile.html"},{"uid":"Microsoft.Azure.Management.HDInsight.Models.OSType","href":"Microsoft.Azure.Management.HDInsight.Models.OSType.html","toc_title":"OSType","level":2,"relative_path_in_depot":"api/hdinsight/Microsoft.Azure.Management.HDInsight.Models.OSType.html"},{"uid":"Microsoft.Azure.Management.HDInsight.Models.Principal","href":"Microsoft.Azure.Management.HDInsight.Models.Principal.html","toc_title":"Principal","level":2,"relative_path_in_depot":"api/hdinsight/Microsoft.Azure.Management.HDInsight.Models.Principal.html"},{"uid":"Microsoft.Azure.Management.HDInsight.Models.QuotaCapability","href":"Microsoft.Azure.Management.HDInsight.Models.QuotaCapability.html","toc_title":"QuotaCapability","level":2,"relative_path_in_depot":"api/hdinsight/Microsoft.Azure.Management.HDInsight.Models.QuotaCapability.html"},{"uid":"Microsoft.Azure.Management.HDInsight.Models.QuotaInfo","href":"Microsoft.Azure.Management.HDInsight.Models.QuotaInfo.html","toc_title":"QuotaInfo","level":2,"relative_path_in_depot":"api/hdinsight/Microsoft.Azure.Management.HDInsight.Models.QuotaInfo.html"},{"uid":"Microsoft.Azure.Management.HDInsight.Models.RdpSettings","href":"Microsoft.Azure.Management.HDInsight.Models.RdpSettings.html","toc_title":"RdpSettings","level":2,"relative_path_in_depot":"api/hdinsight/Microsoft.Azure.Management.HDInsight.Models.RdpSettings.html"},{"uid":"Microsoft.Azure.Management.HDInsight.Models.RDPSettingsParameters","href":"Microsoft.Azure.Management.HDInsight.Models.RDPSettingsParameters.html","toc_title":"RDPSettingsParameters","level":2,"relative_path_in_depot":"api/hdinsight/Microsoft.Azure.Management.HDInsight.Models.RDPSettingsParameters.html"},{"uid":"Microsoft.Azure.Management.HDInsight.Models.RegionalQuotaCapability","href":"Microsoft.Azure.Management.HDInsight.Models.RegionalQuotaCapability.html","toc_title":"RegionalQuotaCapability","level":2,"relative_path_in_depot":"api/hdinsight/Microsoft.Azure.Management.HDInsight.Models.RegionalQuotaCapability.html"},{"uid":"Microsoft.Azure.Management.HDInsight.Models.RegionsCapability","href":"Microsoft.Azure.Management.HDInsight.Models.RegionsCapability.html","toc_title":"RegionsCapability","level":2,"relative_path_in_depot":"api/hdinsight/Microsoft.Azure.Management.HDInsight.Models.RegionsCapability.html"},{"uid":"Microsoft.Azure.Management.HDInsight.Models.Role","href":"Microsoft.Azure.Management.HDInsight.Models.Role.html","toc_title":"Role","level":2,"relative_path_in_depot":"api/hdinsight/Microsoft.Azure.Management.HDInsight.Models.Role.html"},{"uid":"Microsoft.Azure.Management.HDInsight.Models.RuntimeScriptAction","href":"Microsoft.Azure.Management.HDInsight.Models.RuntimeScriptAction.html","toc_title":"RuntimeScriptAction","level":2,"relative_path_in_depot":"api/hdinsight/Microsoft.Azure.Management.HDInsight.Models.RuntimeScriptAction.html"},{"uid":"Microsoft.Azure.Management.HDInsight.Models.RuntimeScriptActionDetail","href":"Microsoft.Azure.Management.HDInsight.Models.RuntimeScriptActionDetail.html","toc_title":"RuntimeScriptActionDetail","level":2,"relative_path_in_depot":"api/hdinsight/Microsoft.Azure.Management.HDInsight.Models.RuntimeScriptActionDetail.html"},{"uid":"Microsoft.Azure.Management.HDInsight.Models.ScriptAction","href":"Microsoft.Azure.Management.HDInsight.Models.ScriptAction.html","toc_title":"ScriptAction","level":2,"relative_path_in_depot":"api/hdinsight/Microsoft.Azure.Management.HDInsight.Models.ScriptAction.html"},{"uid":"Microsoft.Azure.Management.HDInsight.Models.ScriptActionExecutionSummary","href":"Microsoft.Azure.Management.HDInsight.Models.ScriptActionExecutionSummary.html","toc_title":"ScriptActionExecutionSummary","level":2,"relative_path_in_depot":"api/hdinsight/Microsoft.Azure.Management.HDInsight.Models.ScriptActionExecutionSummary.html"},{"uid":"Microsoft.Azure.Management.HDInsight.Models.ServicePrincipal","href":"Microsoft.Azure.Management.HDInsight.Models.ServicePrincipal.html","toc_title":"ServicePrincipal","level":2,"relative_path_in_depot":"api/hdinsight/Microsoft.Azure.Management.HDInsight.Models.ServicePrincipal.html"},{"uid":"Microsoft.Azure.Management.HDInsight.Models.SshProfile","href":"Microsoft.Azure.Management.HDInsight.Models.SshProfile.html","toc_title":"SshProfile","level":2,"relative_path_in_depot":"api/hdinsight/Microsoft.Azure.Management.HDInsight.Models.SshProfile.html"},{"uid":"Microsoft.Azure.Management.HDInsight.Models.SshPublicKey","href":"Microsoft.Azure.Management.HDInsight.Models.SshPublicKey.html","toc_title":"SshPublicKey","level":2,"relative_path_in_depot":"api/hdinsight/Microsoft.Azure.Management.HDInsight.Models.SshPublicKey.html"},{"uid":"Microsoft.Azure.Management.HDInsight.Models.Tier","href":"Microsoft.Azure.Management.HDInsight.Models.Tier.html","toc_title":"Tier","level":2,"relative_path_in_depot":"api/hdinsight/Microsoft.Azure.Management.HDInsight.Models.Tier.html"},{"uid":"Microsoft.Azure.Management.HDInsight.Models.VersionsCapability","href":"Microsoft.Azure.Management.HDInsight.Models.VersionsCapability.html","toc_title":"VersionsCapability","level":2,"relative_path_in_depot":"api/hdinsight/Microsoft.Azure.Management.HDInsight.Models.VersionsCapability.html"},{"uid":"Microsoft.Azure.Management.HDInsight.Models.VersionSpec","href":"Microsoft.Azure.Management.HDInsight.Models.VersionSpec.html","toc_title":"VersionSpec","level":2,"relative_path_in_depot":"api/hdinsight/Microsoft.Azure.Management.HDInsight.Models.VersionSpec.html"},{"uid":"Microsoft.Azure.Management.HDInsight.Models.VirtualNetworkProfile","href":"Microsoft.Azure.Management.HDInsight.Models.VirtualNetworkProfile.html","toc_title":"VirtualNetworkProfile","level":2,"relative_path_in_depot":"api/hdinsight/Microsoft.Azure.Management.HDInsight.Models.VirtualNetworkProfile.html"},{"uid":"Microsoft.Azure.Management.HDInsight.Models.VmSizeCompatibilityFilter","href":"Microsoft.Azure.Management.HDInsight.Models.VmSizeCompatibilityFilter.html","toc_title":"VmSizeCompatibilityFilter","level":2,"relative_path_in_depot":"api/hdinsight/Microsoft.Azure.Management.HDInsight.Models.VmSizeCompatibilityFilter.html"},{"uid":"Microsoft.Azure.Management.HDInsight.Models.VmSizesCapability","href":"Microsoft.Azure.Management.HDInsight.Models.VmSizesCapability.html","toc_title":"VmSizesCapability","level":2,"relative_path_in_depot":"api/hdinsight/Microsoft.Azure.Management.HDInsight.Models.VmSizesCapability.html"},{"uid":"Microsoft.Azure.Management.HDInsight.Models.WindowsOperatingSystemProfile","href":"Microsoft.Azure.Management.HDInsight.Models.WindowsOperatingSystemProfile.html","toc_title":"WindowsOperatingSystemProfile","level":2,"relative_path_in_depot":"api/hdinsight/Microsoft.Azure.Management.HDInsight.Models.WindowsOperatingSystemProfile.html"}]}]
